genesis_ci_tools/__init__.py
genesis_ci_tools/config.py
genesis_ci_tools/constants.py
genesis_ci_tools/elements.py
genesis_ci_tools/logger.py
genesis_ci_tools/node.py
genesis_ci_tools/repo.py
genesis_ci_tools/cmd/__init__.py
genesis_ci_tools/cmd/cli.py
genesis_ci_tools/tests/__init__.py
genesis_ci_tools/tests/unit/__init__.py
genesis_ci_tools/tests/unit/test_basic.py
genesis_ci_tools-1.0.1.dist-info/licenses/AUTHORS
genesis_ci_tools-1.0.1.dist-info/licenses/LICENSE
genesis_ci_tools-1.0.1.dist-info/METADATA
genesis_ci_tools-1.0.1.dist-info/WHEEL
genesis_ci_tools-1.0.1.dist-info/entry_points.txt
genesis_ci_tools-1.0.1.dist-info/pbr.json
genesis_ci_tools-1.0.1.dist-info/top_level.txt
genesis_ci_tools-1.0.1.dist-info/RECORD
