Metadata-Version: 2.4
Name: genesis-ci-tools
Version: 1.0.1
Summary: Genesis CI Tools.
Home-page: https://github.com/infraguys/genesis_ci_tools
Author: Genesis Corporation
Author-email: anton.kremenetsky@gmail.com
Classifier: Intended Audience :: Developers
Classifier: License :: OSI Approved :: Apache Software License
Classifier: Operating System :: POSIX :: Linux
Classifier: Programming Language :: Python
Classifier: Programming Language :: Python :: 3
Classifier: Programming Language :: Python :: 3.8
Classifier: Programming Language :: Python :: 3.10
Classifier: Programming Language :: Python :: 3.11
Classifier: Programming Language :: Python :: 3.12
Classifier: Programming Language :: Python :: 3.13
License-File: LICENSE
License-File: AUTHORS
Requires-Dist: pbr<5.8.1,>=1.10.0
Requires-Dist: click<9.0.0,>=8.1.7
Requires-Dist: pyyaml<7.0.0,>=6.0.0
Requires-Dist: prettytable<4.0.0,>=3.7.0
Requires-Dist: GitPython<4.0.0,>=3.1.30
Requires-Dist: bazooka<2.0.0,>=1.0.0
Requires-Dist: gcl_sdk<2.0.0,>=1.0.0
Dynamic: author
Dynamic: author-email
Dynamic: classifier
Dynamic: description
Dynamic: home-page
Dynamic: license-file
Dynamic: requires-dist
Dynamic: summary
